{
    "id": 196,
    "titulo": "Antonio Negri",
    "url": "https://rodaviva.fapesp.br/materia/196/entrevistados/antonio_negri_2003.htm",
    "arquivo": "antonio_negri_2003.csv",
    "data": "16/12/2003",
    "descricao": "O filósofo e sociólogo faz uma interessante análise das causas e efeitos do poderio econômico dos EUA e de seu império contemporâneo. Fala também de sua polêmica trajetória política e de seus anos na prisão",
    "descricao_externa": "O filósofo e sociólogo faz uma interessante análise das causas e efeitos do poderio econômico dos EUA e de seu império contemporâneo",
    "categoria": [
        "ciências",
        "política"
    ]
}