{
    "id": 506,
    "titulo": "Miguel Nicolelis",
    "url": "https://rodaviva.fapesp.br/materia/506/entrevistados/miguel_nicolelis_2008.htm",
    "arquivo": "miguel_nicolelis_2008.csv",
    "data": "10/11/2008",
    "descricao": "O pesquisador, criador do Instituto Internacional de Neurociências, que fica em Natal (RN), afirma que a ciência deve ser agente de transformação social e que o Brasil precisa “libertar seu sitema educacional do sistema colonial”",
    "descricao_externa": "Considerado uma das maiores autoridades do mundo em neurociência, o cientista brasileiro discorre sobre os avanços desse campo de pesquisa e suas aplicações, especialmente na medicina",
    "categoria": [
        "ciências"
    ],
    "youtube_url": "https://www.youtube.com/watch?v=UNnNiXSjegs"
}