{
    "id": 271,
    "titulo": "Roberto Mangabeira Unger",
    "url": "https://rodaviva.fapesp.br/materia/271/entrevistados/roberto_mangabeira_unger_1993.htm",
    "arquivo": "roberto_mangabeira_unger_1993.csv",
    "data": "17/04/1993",
    "descricao": "Às vésperas do plebiscito sobre o regime e o sistema de governo, o filósofo e jurista fala sobre suas propostas de “reformas revolucionárias” para o país e conta por que filiou-se ao PDT de Brizola",
    "categoria": [
        "política"
    ],
    "youtube_url": "https://www.youtube.com/watch?v=aN1OA0JtStM"
}