{
    "id": 431,
    "titulo": "Yoshiaki Nakano",
    "url": "https://rodaviva.fapesp.br/materia/431/entrevistados/yoshiaki_nakano_2000.htm",
    "arquivo": "yoshiaki_nakano_2000.csv",
    "data": "06/11/2000",
    "descricao": "O administrador e economista avalia que a impossibilidade do governo demitir funcionários e obrigação de pagar aposentadoria integral aos servidores públicos causam um ônus que o Estado não suporta",
    "descricao_externa": "Secretário da Fazenda do estado de São Paulo fala das vantagens do novo sistema eletrônico para pagamento de tributos estaduais, como o IPVA, implantado em sua gestão",
    "categoria": [
        "economia"
    ]
}