{
    "id": 527,
    "titulo": "Mário Covas",
    "url": "https://rodaviva.fapesp.br/materia/527/entrevistados/mario_covas_1992.htm",
    "arquivo": "mario_covas_1992.csv",
    "data": "09/03/1992",
    "descricao": "Político paulista de renome nacional, Covas convoca uma cruzada contra a corrupção e discute temas como valor do IPTU, mercado de informática, fidelidade partidária e voto distrital",
    "descricao_externa": "Um dos fundadores do PSDB e liderança na Constituinte (1987-88), Covas refuta o rótulo de indeciso e justifica o apoio a Lula em 1989, no segundo turno, contra Collor",
    "categoria": [
        "política"
    ]
}