{
    "id": 658,
    "titulo": "Olacyr de Moraes",
    "url": "https://rodaviva.fapesp.br/materia/658/entrevistados/olacyr_de_moraes_1993.htm",
    "arquivo": "olacyr_de_moraes_1993.csv",
    "data": "04/10/1993",
    "descricao": "Em meio à implantação de uma nova moeda no Brasil e com a expectativa da revisão constitucional, um dos maiores exportadores de soja do país fala dos anseios do empresariado e defende as privatizações",
    "descricao_externa": "Com um patrimônio avaliado em um bilhão de dólares, o “rei da soja” fala da necessidade de se realizar privatizações no país e do futuro de suas empresas",
    "categoria": [
        "economia",
        "política"
    ],
    "youtube_url": "https://www.youtube.com/watch?v=GJO1A7xKz3I"
}