{
    "id": 254,
    "titulo": "Pat O`Hare",
    "url": "https://rodaviva.fapesp.br/materia/254/entrevistados/pat_o`hare_2004.htm",
    "arquivo": "pat_ohare_2004.csv",
    "data": "06/09/2004",
    "descricao": "O objetivo principal do programa de redução de danos é diminuir ao máximo os riscos que correm os usuários de drogas, injetáveis principalmente, como os de contrair aids e hepatite",
    "descricao_externa": "Fornecer seringas novas e trocar drogas pesadas por mais leves, para o usuário, são as mais importantes - e não menos polêmicas - medidas propostas pelo diretor da Associação Internacional de Redução de Danos",
    "youtube_url": "https://www.youtube.com/watch?v=uv2rOab1WPI"
}